{
    "origin": [
        "#issue.capitalize#. #consequence.capitalize#.", 
        "#issue.capitalize#. #disruption.capitalize#.", 
        "#issue.capitalize#. #disruption.capitalize#.", 
        "#consequence.capitalize# due to #issue#.", 
        "#disruption.capitalize# due to #issue#.", 
        "#disruption.capitalize# due to #issue#.", 
        "#infestation#"
    ], 
    "monster": [
        "Godzilla", 
        "Kamacuras", 
        "Destoroyah", 
        "Godzilla Junior", 
        "Biollante", 
        "Gigan", 
        "Gorosaurus", 
        "Ebirah", 
        "Baragon", 
        "King Caesar", 
        "Orga", 
        "Varan", 
        "Moguera", 
        "Kumonga", 
        "Minilla", 
        "MUTO", 
        "Hedorah", 
        "Mechagodzilla", 
        "SpaceGodzilla", 
        "Battra", 
        "Megaguirus", 
        "Anguirus", 
        "King Ghidorah", 
        "Mothra", 
        "Meganulon", 
        "Miki Saegusa", 
        "King Kong", 
        "Rodan", 
        "Monster X"
    ], 
    "animal_modifier": [
        "", 
        "", 
        "", 
        "large ", 
        "aggressive ", 
        "rare ", 
        "sleeping ", 
        "bewildered ", 
        "drunk ", 
        "distressed ", 
        "unkempt ", 
        "weak ", 
        "curious ", 
        "migrating "
    ], 
    "market_issue": [
        "falling values on the #market#", 
        "heavy trading on the #market#", 
        "suspicious trades on the #market#"
    ], 
    "number": [
        "two", 
        "five", 
        "ten", 
        "twenty"
    ], 
    "hazard": [
        "earthquake", 
        "supervolcano", 
        "debris flow", 
        "rockfall", 
        "solifluction", 
        "cryoseism", 
        "hyperconcentrated flow", 
        "mass wasting", 
        "flood basalt", 
        "tsunami", 
        "volcano", 
        "dry quicksand", 
        "quicksand", 
        "megatsunami", 
        "lahar", 
        "fenambosy chevron", 
        "ferguson landslide", 
        "geohazard", 
        "mudflow", 
        "bergschrund", 
        "limnic eruption", 
        "earthflow", 
        "predator trap", 
        "mazuku"
    ], 
    "expectation": [
        "likely", 
        "expected", 
        "predicted"
    ], 
    "hours": [
        "00", 
        "01", 
        "02", 
        "03", 
        "04", 
        "05", 
        "06", 
        "07", 
        "08", 
        "09", 
        "10", 
        "11", 
        "12", 
        "13", 
        "14", 
        "15", 
        "16", 
        "17", 
        "18", 
        "19", 
        "20", 
        "21", 
        "22", 
        "23"
    ], 
    "infestation_type": [
        "", 
        "an infestation of "
    ], 
    "market": [
        "Vara\u017edin Stock Exchange", 
        "OPEX (Stock Exchange)", 
        "Burgundy (stock market)", 
        "Mandatory quote period", 
        "Kazakhstan Stock Exchange", 
        "Gibraltar Stock Exchange", 
        "Federation of Euro-Asian Stock Exchanges", 
        "CEE Stock Exchange Group", 
        "Channel Islands Securities Exchange", 
        "FUTOP", 
        "Sarajevo Stock Exchange", 
        "Ukrainian Universal Exchange", 
        "Bratislava Stock Exchange", 
        "Armenian Stock Exchange", 
        "Georgian Stock Exchange", 
        "NOREX", 
        "Dundee Stock Exchange", 
        "Baku Stock Exchange", 
        "Budapest Stock Exchange", 
        "Bulgarian Stock Exchange \u2013 Sofia", 
        "Borsa Italiana", 
        "Glasgow Stock Exchange", 
        "Faroese Securities Market", 
        "Ukrainian Exchange", 
        "Scottish Stock Exchange", 
        "Euro.nm", 
        "Zagreb Stock Exchange", 
        "Cyprus Stock Exchange", 
        "SIX Swiss Exchange", 
        "Tallinn Stock Exchange", 
        "Euronext", 
        "Stockholm Stock Exchange", 
        "Ljubljana Stock Exchange", 
        "Malta Stock Exchange", 
        "Banja Luka Stock Exchange", 
        "Berne eXchange", 
        "Brussels Stock Exchange", 
        "Copenhagen Stock Exchange", 
        "Euronext Paris", 
        "Saint Petersburg Stock Exchange", 
        "Riga Stock Exchange", 
        "Nordic Derivatives Exchange", 
        "Stock exchanges in Ukraine", 
        "BELFOX", 
        "Athens Stock Exchange", 
        "Iceland Stock Exchange", 
        "Sibiu Stock Exchange", 
        "Euronext Lisbon", 
        "Prague Stock Exchange", 
        "Helsinki Stock Exchange", 
        "Wiener B\u00f6rse", 
        "Borsa Istanbul", 
        "Irish Stock Exchange", 
        "Tirana Stock Exchange", 
        "NEX Stock Exchange", 
        "Nordic Growth Market", 
        "PFTS Ukraine Stock Exchange", 
        "2 Haymarket", 
        "Edinburgh Stock Exchange", 
        "Cotation Assist\u00e9e en Continu", 
        "Bolsa de Madrid", 
        "Commodity Exchange Bratislava", 
        "Luxembourg Stock Exchange", 
        "Macedonian Stock Exchange", 
        "Montenegro Stock Exchange", 
        "Paris Bourse", 
        "Euronext Amsterdam", 
        "Amsterdam Stock Exchange", 
        "Bucharest Stock Exchange", 
        "NASDAQ OMX Vilnius", 
        "Belgrade Stock Exchange", 
        "First North", 
        "Channel Islands Stock Exchange", 
        "K\u00f6nigsberg Stock Exchange", 
        "Options Market France", 
        "Belarusian Currency and Stock Exchange", 
        "Uniform Symbology", 
        "GXG Markets", 
        "Euronext Brussels", 
        "Royal Exchange, Edinburgh"
    ], 
    "weather": [
        "derecho", 
        "hypercane", 
        "winter storm", 
        "european windstorm", 
        "tropical cyclone", 
        "upper-atmospheric lightning", 
        "haboob", 
        "effects of tropical cyclones", 
        "bow echo", 
        "lightning activity level", 
        "tornado preparedness", 
        "genoa low", 
        "rainband", 
        "el ni\u00f1o", 
        "perfect storm", 
        "kalla kadal", 
        "arkstorm", 
        "cryoseism", 
        "radius of maximum wind", 
        "jumble ice", 
        "zud", 
        "freezing rain", 
        "microburst", 
        "norwesters", 
        "severe thunderstorm outbreak", 
        "spanish plume", 
        "tree well", 
        "snowsquall", 
        "ice dam", 
        "air-mass thunderstorm", 
        "el ni\u00f1o\u2013southern oscillation", 
        "hot tower", 
        "central dense overcast", 
        "la ni\u00f1a", 
        "extreme weather", 
        "ice jacking", 
        "freezing drizzle", 
        "maritime impacts of volcanic eruptions"
    ], 
    "caution": [
        "caution", 
        "care"
    ], 
    "disrupted": [
        "will terminate at #station#", 
        "is delayed", 
        "is cancelled", 
        "is running #duration# late", 
        "will be diverted via #station#", 
        "will #maybe_call# call at #station#"
    ], 
    "infestation": "#station# closed due to #infestation_type##animal_or_pest.s#. #infestation_disruption.capitalize#", 
    "duration": "#number# #unit.s#", 
    "suspected": [
        "suspected", 
        "observed"
    ], 
    "modified_animal": "#animal_modifier##animal#", 
    "unit": [
        "minute", 
        "minute", 
        "hour"
    ], 
    "infestation_disruption": [
        "delays expected", 
        "services will run via #station# for the next #duration#.", 
        "replacement bus service from #station#."
    ], 
    "rodent": [
        "Eurasian harvest mouse", 
        "Wrangel Island lemming", 
        "Roach's mouse-tailed dormouse", 
        "Majorcan giant dormouse", 
        "Skomer vole", 
        "Spermophilus", 
        "St Kilda field mouse", 
        "European water vole", 
        "Field vole", 
        "Red squirrel", 
        "Marmot", 
        "Algerian mouse", 
        "Alpine field mouse", 
        "Alpine marmot", 
        "Armenian birch mouse", 
        "Balkan snow vole", 
        "Bank vole", 
        "Bavarian pine vole", 
        "Black rat", 
        "Calabria pine vole", 
        "Caucasian squirrel", 
        "Ciscaucasian hamster", 
        "Common vole", 
        "Crested porcupine", 
        "Crete spiny mouse", 
        "Cypriot mouse", 
        "Cyprus spiny mouse", 
        "Edible dormouse", 
        "Eurasian beaver", 
        "European ground squirrel", 
        "European hamster", 
        "European snow vole", 
        "Garden dormouse", 
        "Gray dwarf hamster", 
        "Hazel dormouse", 
        "Lusitanian pine vole", 
        "Northern mole vole", 
        "Northern red-backed vole", 
        "Norway lemming", 
        "Sandy mole-rat", 
        "Siberian flying squirrel", 
        "Southwestern water vole", 
        "Steppe lemming", 
        "Steppe mouse", 
        "Striped field mouse", 
        "Tatra pine vole", 
        "Tundra vole", 
        "Ural field mouse", 
        "Wood mouse", 
        "Yellow-necked mouse", 
        "St Kilda house mouse", 
        "Eastern grey squirrels in Europe", 
        "Bobak marmot", 
        "Robert's snow vole", 
        "Orkney vole"
    ], 
    "modified_monster": "#animal_modifier##monster#", 
    "cause": [
        "#rodent#", 
        "#amphibian#", 
        "#weather#", 
        "#hazard#"
    ], 
    "service": "the #time# from #station# to #station#", 
    "disruption": [
        "#service# #disrupted#"
    ], 
    "crime_organisation": [
        "Cult of the Unwritten Book", 
        "Terror Titans", 
        "Justice Lords", 
        "Robot Renegades", 
        "S.P.I.D.E.R.", 
        "Shadowspire", 
        "H.I.V.E.", 
        "Secret Society of Super Villains", 
        "Red Lantern Corps", 
        "Dark Circle", 
        "Injustice Gang", 
        "Injustice League", 
        "Injustice Society", 
        "Court of Owls", 
        "Suicide Squad", 
        "Pentacle", 
        "League of Super-Assassins", 
        "League of Assassins", 
        "Circus of Strange", 
        "Intergang", 
        "Jokerz", 
        "Titans East", 
        "Sinestro Corps", 
        "Anti-Justice League", 
        "Brotherhood of Dada", 
        "Death Eater", 
        "Stanfield Organization", 
        "Barksdale Organization", 
        "Jhereg", 
        "Orion Syndicate", 
        "Kuuma Empire", 
        "Organizations of Alias", 
        "Sons of Anarchy Motorcycle Club", 
        "World of Ghost in the Shell", 
        "Galactor", 
        "Faction Paradox", 
        "Shadow Thieves", 
        "Wallenquist Organization", 
        "Grove Street Families", 
        "New Day Co-Op", 
        "Axe Gang", 
        "Foot Clan", 
        "Iquan's Party", 
        "Beagle Boys", 
        "SPECTRE", 
        "Greeks of The Wire", 
        "Tiger Mafia"
    ], 
    "minutes": [
        "00", 
        "01", 
        "02", 
        "03", 
        "04", 
        "05", 
        "06", 
        "07", 
        "08", 
        "09", 
        "10", 
        "11", 
        "12", 
        "13", 
        "14", 
        "15", 
        "16", 
        "17", 
        "18", 
        "19", 
        "20", 
        "21", 
        "22", 
        "23", 
        "24", 
        "25", 
        "26", 
        "27", 
        "28", 
        "29", 
        "30", 
        "31", 
        "32", 
        "33", 
        "34", 
        "35", 
        "36", 
        "37", 
        "38", 
        "39", 
        "40", 
        "41", 
        "42", 
        "43", 
        "44", 
        "45", 
        "46", 
        "47", 
        "48", 
        "49", 
        "50", 
        "51", 
        "52", 
        "53", 
        "54", 
        "55", 
        "56", 
        "57", 
        "58", 
        "59"
    ], 
    "location": [
        "in the #station# area", 
        "between #station# and #station#", 
        "outside #station#", 
        "on the #station# line"
    ], 
    "crime": [
        "#crime_organisation# #crime_activity# #suspected# #location#"
    ], 
    "crime_activity": [
        "activity", 
        "operations"
    ], 
    "animal_or_pest": [
        "#animal#", 
        "#pest#"
    ], 
    "station": [
        "Bradford Forster Square", 
        "Appleby", 
        "Hessle", 
        "Howden", 
        "Hutton Cranswick", 
        "Bryn", 
        "Dalton", 
        "Heysham Port", 
        "Morecambe", 
        "Silverdale", 
        "Dore and Totley", 
        "Guiseley", 
        "Penistone", 
        "Wakefield Kirkgate", 
        "New Clee", 
        "Grindleford", 
        "Kents Bank", 
        "Lytham", 
        "New Mills Newtown", 
        "Patricroft", 
        "Roose", 
        "Swinton (South Yorkshire)", 
        "Smithy Bridge", 
        "Kirkstall Forge", 
        "Meadowhall Interchange", 
        "Oldham Mumps", 
        "Haydon Bridge", 
        "Aspatria", 
        "Hexham", 
        "Manchester Oxford Road", 
        "Manors", 
        "Sowerby Bridge", 
        "Allerton", 
        "Bramley (West Yorkshire)", 
        "Brighouse", 
        "Chassen Road", 
        "Featherstone", 
        "Flixton", 
        "Halewood", 
        "Halifax", 
        "Hough Green", 
        "Humphrey Park", 
        "Knottingley", 
        "Lea Green", 
        "Mossley Hill", 
        "New Pudsey", 
        "Pontefract Monkhill", 
        "Pontefract Tanshelf", 
        "St Helens Central", 
        "St Helens Junction", 
        "Streethouse", 
        "Trafford Park", 
        "Urmston", 
        "Wavertree Technology Park", 
        "West Allerton", 
        "Widnes", 
        "Castleford", 
        "Glasshoughton", 
        "Outwood", 
        "Woodlesford", 
        "Buckshaw Parkway", 
        "Bare Lane", 
        "Darnall", 
        "Manchester Victoria station", 
        "Micklefield", 
        "Dalston", 
        "Euxton Balshaw Lane", 
        "Barnsley Interchange", 
        "Blackrod", 
        "Bolton Interchange", 
        "Bootle", 
        "Braystones", 
        "Broad Green", 
        "Bromley Cross", 
        "Chapeltown", 
        "Clifton (Manchester)", 
        "Corkickle", 
        "Darwen", 
        "Deansgate", 
        "Drigg", 
        "Entwistle", 
        "Farnworth", 
        "Flimby", 
        "Foxfield", 
        "Green Road", 
        "Hall i' th' Wood", 
        "Harrington", 
        "Horwich Parkway", 
        "Kearsley", 
        "Kirkby-in-Furness", 
        "Lostock", 
        "Maryport", 
        "Meols Cop", 
        "Mexborough", 
        "Mill Hill (Lancashire)", 
        "Millom", 
        "Moses Gate", 
        "Nethertown", 
        "Orrell", 
        "Parton", 
        "Pemberton", 
        "Ravenglass", 
        "Salford Crescent", 
        "Sellafield", 
        "Silecroft", 
        "St Bees", 
        "Upholland", 
        "Whitehaven", 
        "Wigan Wallgate", 
        "Wigton", 
        "Wombwell", 
        "Workington", 
        "Accrington", 
        "Adwick", 
        "Althorpe", 
        "Askam", 
        "Bamber Bridge", 
        "Bamford", 
        "Bentley (South Yorkshire)", 
        "Bescar Lane", 
        "Bolton-on-Dearne", 
        "Burnley Manchester Road", 
        "Burscough Junction", 
        "Buxton", 
        "Chapel-en-le-Frith", 
        "Cherry Tree", 
        "Chinley", 
        "Chorley", 
        "Church and Oswaldtwistle", 
        "Colne", 
        "Congleton", 
        "Conisbrough", 
        "Croston", 
        "Crowle", 
        "Disley", 
        "Dove Holes", 
        "Dronfield", 
        "Fitzwilliam", 
        "Furness Vale", 
        "Gathurst", 
        "Gatley", 
        "Glazebrook", 
        "Goldthorpe", 
        "Goole", 
        "Habrough", 
        "Hatfield and Stainforth", 
        "Hathersage", 
        "Hazel Grove", 
        "Heald Green", 
        "Hebden Bridge", 
        "Heworth Interchange", 
        "Kirk Sandall", 
        "Kiveton Bridge", 
        "Kiveton Park", 
        "Langho", 
        "Leyland", 
        "Lostock Hall", 
        "Middlewood", 
        "Moorthorpe", 
        "New Lane", 
        "New Mills Central", 
        "Padgate", 
        "Rishton", 
        "Rufford", 
        "Sankey", 
        "Shireoaks", 
        "South Elmsall", 
        "Thorne North", 
        "Thorne South", 
        "Thurnscoe", 
        "Whaley Bridge", 
        "Wilmslow", 
        "Woodhouse", 
        "Worksop", 
        "Atherton", 
        "Barrow Haven", 
        "Daisy Hill", 
        "Hindley", 
        "Thatto Heath", 
        "Barton-on-Humber", 
        "Eccleston Park", 
        "Gainsborough Central", 
        "Garswood", 
        "Hapton", 
        "Hoscar", 
        "Huncoat", 
        "Navigation Road station", 
        "Poynton", 
        "Prescot", 
        "Reddish South", 
        "Cottam (Preston)", 
        "Altrincham Interchange", 
        "Arram", 
        "Cottingley", 
        "Giggleswick", 
        "Pegswood", 
        "Poppleton", 
        "Goxhill", 
        "Darton", 
        "Earlestown", 
        "Elsecar", 
        "Morpeth", 
        "Glossop", 
        "Huyton", 
        "Nelson", 
        "Clapham", 
        "Egton", 
        "Manchester United Football Ground", 
        "Rawcliffe", 
        "Adlington (Cheshire)", 
        "Appley Bridge", 
        "Bramhall", 
        "Broadbottom", 
        "Chelford", 
        "Cuddington", 
        "Dean Lane", 
        "Delamere", 
        "Dinting", 
        "Flowery Field", 
        "Goostrey", 
        "Greenbank", 
        "Hag Fold", 
        "Handforth", 
        "Holmes Chapel", 
        "Ince (Wigan)", 
        "Ince and Elton", 
        "Knutsford", 
        "Lostock Gralam", 
        "Mobberley", 
        "Moorside", 
        "Mouldsworth", 
        "Northwich", 
        "Parbold", 
        "Pleasington", 
        "Plumley", 
        "Prestbury", 
        "Rainhill", 
        "Rose Grove", 
        "Sandbach", 
        "Stanlow and Thornton", 
        "Styal", 
        "Swinton (Manchester)", 
        "Walkden", 
        "Westhoughton", 
        "Whiston", 
        "Ansdell and Fairhaven", 
        "Blackpool North", 
        "Blackpool Pleasure Beach", 
        "Blackpool South", 
        "Denton", 
        "Kirkham and Wesham", 
        "Layton", 
        "Moss Side", 
        "Poulton-le-Fylde", 
        "Squires Gate", 
        "St Annes-on-the-Sea", 
        "Salwick", 
        "Armathwaite", 
        "Battersby", 
        "Bempton", 
        "Beverley", 
        "Bridlington", 
        "British Steel Redcar", 
        "Castleton Moor", 
        "Cattal", 
        "Commondale", 
        "Cottingham", 
        "Dent", 
        "Driffield", 
        "Eaglescliffe", 
        "Filey", 
        "Gargrave", 
        "Garsdale", 
        "Glaisdale", 
        "Great Ayton", 
        "Grosmont", 
        "Gypsy Lane", 
        "Hammerton", 
        "Harrogate", 
        "Hartlepool", 
        "Hornbeam Park", 
        "Horton-in-Ribblesdale", 
        "Hunmanby", 
        "Kildale", 
        "Knaresborough", 
        "Lazonby and Kirkoswald", 
        "Lealholm", 
        "Longbeck", 
        "Marske", 
        "Marton", 
        "Nafferton", 
        "Newton Aycliffe", 
        "North Road", 
        "Nunthorpe", 
        "Pannal", 
        "Ribblehead", 
        "Ruswarp", 
        "Saltburn", 
        "Seaham", 
        "Settle", 
        "Sleights", 
        "South Bank, North Yorkshire", 
        "Starbeck", 
        "Stockton", 
        "Teesside Airport", 
        "Weeton", 
        "Wennington", 
        "Whitby", 
        "Bardon Mill", 
        "Corbridge", 
        "Hadfield", 
        "Hattersley", 
        "Kirton Lindsey", 
        "Newton for Hyde", 
        "Saltmarshe", 
        "Brigg", 
        "Eastrington", 
        "Gilberdyke", 
        "Great Coates", 
        "Grimsby Docks", 
        "Healing", 
        "Hensall", 
        "New Holland", 
        "Snaith", 
        "Stallingborough", 
        "Thornton Abbey", 
        "Ulceby", 
        "Whitley Bridge", 
        "Wressle", 
        "Blaydon", 
        "Brampton (Cumbria)", 
        "Dunston", 
        "Hale", 
        "Oldham Werneth", 
        "Rotherham Central", 
        "Belle Vue", 
        "Dinsdale", 
        "East Didsbury", 
        "Heighington", 
        "Long Preston", 
        "Ardwick", 
        "Roby", 
        "Hellifield", 
        "Haltwhistle", 
        "Brierfield", 
        "Burnley Barracks", 
        "Rainford", 
        "Redcar Central", 
        "Redcar East", 
        "Alnmouth", 
        "Acklington", 
        "Bentham", 
        "Adlington (Lancashire)", 
        "Irlam", 
        "James Cook", 
        "Mauldeth Road", 
        "Normanton", 
        "Alderley Edge", 
        "Danby", 
        "Eccles", 
        "Godley", 
        "Rose Hill Marple", 
        "Horsforth Woodside", 
        "Edge Hill", 
        "Seascale", 
        "Ashley", 
        "Blackburn", 
        "Edale", 
        "Hope (Derbyshire)", 
        "MetroCentre", 
        "Ramsgreave and Wilpshire", 
        "Wetheral", 
        "Allens West", 
        "Chathill", 
        "Kirkby Stephen", 
        "Langwathby", 
        "Prudhoe", 
        "Riding Mill", 
        "Shildon", 
        "Stocksfield", 
        "Widdrington", 
        "Wylam", 
        "Billingham", 
        "Burnage", 
        "Burnley Central", 
        "Burscough Bridge", 
        "Cheadle Hulme", 
        "Clitheroe", 
        "Seaton Carew", 
        "Whalley", 
        "Broomfleet", 
        "Bishop Auckland", 
        "Cark and Cartmel", 
        "Salford Central", 
        "Ashton-under-Lyne", 
        "Baildon", 
        "Batley", 
        "Ben Rhydding", 
        "Bingley", 
        "Burley-in-Wharfedale", 
        "Burley Park", 
        "Chester-le-Street", 
        "Church Fenton", 
        "Cononley", 
        "Cramlington", 
        "Cross Gates", 
        "Crossflatts", 
        "Davenport (Stockport)", 
        "Deighton", 
        "Dodworth", 
        "East Garforth", 
        "Frizinghall", 
        "Garforth", 
        "Greenfield", 
        "Headingley", 
        "Heaton Chapel", 
        "Horsforth", 
        "Ilkley", 
        "Keighley", 
        "Levenshulme", 
        "Lockwood", 
        "Marsden", 
        "Menston", 
        "Mirfield", 
        "Morley", 
        "Mossley", 
        "Mytholmroyd", 
        "Newton-le-Willows", 
        "Pontefract Baghill", 
        "Ravensthorpe", 
        "Saltaire", 
        "Sherburn-in-Elmet", 
        "Shipley", 
        "Silkstone Common", 
        "Skipton", 
        "Slaithwaite", 
        "South Milford", 
        "Steeton and Silsden", 
        "Todmorden", 
        "Ulleskelf", 
        "Walsden", 
        "Woodsmoor", 
        "Ashburys", 
        "Bredbury", 
        "Brinnington", 
        "Castleton", 
        "Fairfield (Greater Manchester)", 
        "Ferriby", 
        "Gorton", 
        "Guide Bridge", 
        "Hyde Central", 
        "Hyde North", 
        "Littleborough", 
        "Marple", 
        "Mills Hill", 
        "Moston", 
        "Reddish North", 
        "Rochdale", 
        "Romiley", 
        "Ryder Brow", 
        "Strines", 
        "Woodley", 
        "Berry Brow", 
        "Brockholes", 
        "Denby Dale", 
        "Honley", 
        "Shepley", 
        "Stocksmoor", 
        "Sunderland station"
    ], 
    "pest": [
        "Turkestan cockroach", 
        "Silverfish", 
        "Black carpenter ant", 
        "American cockroach", 
        "Red flour beetle", 
        "Banded sugar ant", 
        "Mezium americanum", 
        "Boxelder bug", 
        "Oriental cockroach", 
        "Termite", 
        "Bed bug", 
        "Black-headed sugar ant", 
        "Confused flour beetle", 
        "Powderpost beetle", 
        "Housefly", 
        "Thylodrias", 
        "Argentine ant", 
        "Destructive flour beetle", 
        "Forficula auricularia", 
        "Scutigera coleoptrata", 
        "Incisitermes minor", 
        "Deathwatch beetle", 
        "Jack jumper ant", 
        "Red imported fire ant", 
        "Rasberry crazy ant", 
        "Golden spider beetle", 
        "Forelius pruinosus", 
        "German cockroach"
    ], 
    "time": [
        "#hours#:#minutes#"
    ], 
    "animal": [
        "#rodent#", 
        "#amphibian#"
    ], 
    "sighted": [
        "sighted near", 
        "on the tracks near", 
        "reported near", 
        "approaching"
    ], 
    "consequence": [
        "delays of #modifier##duration# #expectation#", 
        "disruption #expectation# for the next #duration#", 
        "limited catering on #service#", 
        "#caution# advised", 
        "replacement bus service between #station# and #station#", 
        "tickets will be accepted on services via #station#"
    ], 
    "amphibian": [
        "Ambrosi's cave salamander", 
        "Levant water frog", 
        "North African fire salamander", 
        "Imperial cave salamander", 
        "Macedonian crested newt", 
        "Common toad", 
        "Marsh frog", 
        "Natterjack toad", 
        "Northern crested newt", 
        "Palmate newt", 
        "Balkan frog", 
        "Balearic green toad", 
        "Agile frog", 
        "Albanian water frog", 
        "Alpine salamander", 
        "Apennine yellow-bellied toad", 
        "Common frog", 
        "Common parsley frog", 
        "Corsican fire salamander", 
        "Danube crested newt", 
        "Edible frog", 
        "Epirus water frog", 
        "European green toad", 
        "European tree frog", 
        "Fire salamander", 
        "Greek stream frog", 
        "Iberian frog", 
        "Italian agile frog", 
        "Italian cave salamander", 
        "Italian crested newt", 
        "Italian edible frog", 
        "Italian newt", 
        "Italian stream frog", 
        "Marbled newt", 
        "Mediterranean tree frog", 
        "Moor frog", 
        "Northern spectacled salamander", 
        "Olm", 
        "Pelobates cultripes", 
        "Pelobates fuscus", 
        "Pelobates syriacus", 
        "Pool frog", 
        "Sardinian tree frog", 
        "Smooth newt", 
        "Spectacled salamander", 
        "Cretan frog", 
        "Balkan-Anatolian crested newt", 
        "Bosca's newt", 
        "Caucasian toad", 
        "Italian tree frog", 
        "Lanza's alpine salamander", 
        "Brown cave salamander", 
        "Italian pool frog", 
        "Karpathos frog", 
        "Monte Albo cave salamander", 
        "Pelophylax kl. grafi", 
        "Supramonte cave salamander", 
        "Sicilian green toad", 
        "Triturus"
    ], 
    "problem": [
        "technical issue", 
        "staff shortage", 
        "signal failure"
    ], 
    "modifier": [
        "at least ", 
        "up to ", 
        "over "
    ], 
    "issue": [
        "reports of #cause.s# #location#", 
        "reports of #cause.s# #location#", 
        "#problem.s# #location# caused by #cause.s#", 
        "#problem.s# #location# caused by #cause.s#", 
        "#modified_animal.a# #sighted# #station#", 
        "#monster# #sighted# #station#", 
        "#modified_monster.a# #sighted# #station#", 
        "#quantity##animal.s# reported at #station#", 
        "#quantity##animal.s# reported at #station#", 
        "#quantity##animal.s# expected #location#", 
        "#quantity##animal.s# expected #location#"
    ], 
    "maybe_call": [
        "no longer", 
        "additionally"
    ], 
    "quantity": [
        "high volumes of ", 
        "several ", 
        "numerous ", 
        "unprecedented levels of ", 
        "groups of ", 
        "", 
        "", 
        "#number# "
    ]
}